AUTHORS
ChangeLog
LICENSE
MANIFEST.in
README.md
requirements.txt
setup.cfg
setup.py
test-requirements.txt
tox.ini
etc/event_definitions.yaml
etc/logging.conf
etc/pipelines.yaml
etc/triggers.yaml
etc/winchester.yaml
tests/test_db.py
tests/test_debugger.py
tests/test_definition.py
tests/test_notabene.py
tests/test_pipeline_manager.py
tests/test_time_sync.py
tests/test_trigger_manager.py
tests/test_usage_handler.py
winchester/__init__.py
winchester/config.py
winchester/debugging.py
winchester/definition.py
winchester/models.py
winchester/pipeline_handler.py
winchester/pipeline_manager.py
winchester/time_sync.py
winchester/trigger_manager.py
winchester/worker.py
winchester/yagi_handler.py
winchester.egg-info/PKG-INFO
winchester.egg-info/SOURCES.txt
winchester.egg-info/dependency_links.txt
winchester.egg-info/entry_points.txt
winchester.egg-info/not-zip-safe
winchester.egg-info/pbr.json
winchester.egg-info/requires.txt
winchester.egg-info/top_level.txt
winchester/db/__init__.py
winchester/db/alembic_command.py
winchester/db/db_admin.py
winchester/db/interface.py
winchester/db/migrations/README
winchester/db/migrations/__init__.py
winchester/db/migrations/env.py
winchester/db/migrations/script.py.mako
winchester/db/migrations/versions/3ab6d7bf80cd_.py
winchester/db/migrations/versions/44289d1492e6_.py