Metadata-Version: 1.0
Name: winchester
Version: 0.5.dev28
Summary: An OpenStack notification event processing library.
Home-page: https://github.com/stackforge/stacktach-winchester
Author: Monsyne Dragon
Author-email: mdragon@rackspace.com
License: Apache-2
Keywords: stacktach
Platform: UNKNOWN
